An_lib/__init__.py
An_lib/src/__init__.py
An_lib/src/cat.py
An_lib/src/dog.py
An_lib/test/__init__.py
An_lib/test/test_dog.py
cat_dog_lib/__init__.py
cat_dog_lib/src/__init__.py
cat_dog_lib/src/cat.py
cat_dog_lib/src/dog.py
cat_dog_lib/src/laboratory/__init__.py
cat_dog_lib/src/laboratory/doctor.py
cat_dog_lib/src/laboratory/machine.py
cat_dog_lib/test/__init__.py
cat_dog_lib/test/test_dog.py
cat_dog_lib-0.0.2.dist-info/METADATA
cat_dog_lib-0.0.2.dist-info/WHEEL
cat_dog_lib-0.0.2.dist-info/top_level.txt
cat_dog_lib-0.0.2.dist-info/RECORD
