Metadata-Version: 2.1
Name: cat-dog-lib
Version: 0.0.2
Summary: Mô tả ngắn
Home-page: https://github.com/anthule123/first_package_An
Author: anthule123
Author-email: lethithuan_t63@hus.edu.vn
License: MIT
Classifier: License :: OSI Approved :: MIT License
Classifier: Programming Language :: Python :: 3.10
Classifier: Operating System :: OS Independent
Requires-Python: >=3.10
Provides-Extra: dev
Requires-Dist: pytest (>=7.0) ; extra == 'dev'
Requires-Dist: twine (>=3.4.2) ; extra == 'dev'
